Cargo.lock
Cargo.toml
LICENSE
MANIFEST.in
README.md
pyproject.toml
src/errors.rs
src/lib.rs
src/parse.rs
src/post.rs
src/django_markdown_database.egg-info/PKG-INFO
src/django_markdown_database.egg-info/SOURCES.txt
src/django_markdown_database.egg-info/dependency_links.txt
src/django_markdown_database.egg-info/requires.txt
src/django_markdown_database.egg-info/top_level.txt
src/markdowndb/__init__.py
src/markdowndb/base.py
src/markdowndb/mixins.py