Metadata-Version: 2.4
Name: django-markdown-database
Version: 0.1.2
Summary: Mount a directory of markdown files as a sqlite virtual table in Django
Author-email: Paul Traylor <kungfudiscomonkey@gmail.com>
License-Expression: MIT
Project-URL: Homepage, https://codeberg.org/kfdm/django-markdown-database
Project-URL: Issues, https://codeberg.org/kfdm/django-markdown-database/issues
Classifier: Development Status :: 3 - Alpha
Classifier: Framework :: Django :: 5.2
Classifier: Framework :: Django
Classifier: Operating System :: OS Independent
Classifier: Programming Language :: Python :: 3
Classifier: Programming Language :: Rust
Requires-Python: >=3.12
License-File: LICENSE
Requires-Dist: django>=5.2.0
Dynamic: license-file
